<?xml version="1.0" encoding="UTF-8"?>
<fits xmlns="http://hul.harvard.edu/ois/xml/ns/fits/fits_output" xmlns:xsi="http://www.w3.org/2001/XMLSchema-instance" xsi:schemaLocation="http://hul.harvard.edu/ois/xml/ns/fits/fits_output http://hul.harvard.edu/ois/xml/xsd/fits/fits_output.xsd" version="1.5.5" timestamp="3/4/23, 12:11 AM">
  <identification>
    <identity format="TIFF EXIF" mimetype="image/tiff" toolname="FITS" toolversion="1.5.5">
      <tool toolname="Jhove" toolversion="1.20.1" />
      <tool toolname="Exiftool" toolversion="11.54" />
      <version toolname="Jhove" toolversion="1.20.1">6.0</version>
    </identity>
  </identification>
  <fileinfo>
    <size toolname="Jhove" toolversion="1.20.1">53798106</size>
    <creatingApplicationName toolname="Exiftool" toolversion="11.54" status="SINGLE_RESULT">.[global].dpi_mode= flexible.dpi=300.scanmode=wait.colormode=truecolor.docmode=4.docheight = 0.wa_x = 1.wa_y = 1.serial=S2N-BASE-V2-001999311b2d.FirmwareVersion=5.10..[autofocus].focus_x = -1000.focus_y = 500.focus_w = 2500...[scan].autofocus=on.descreening=0.cms=off.speed=1.bright=178.contr=142.gamma=15.gain_r=0.gain_g=0.gain_b=0.aexp_black=10.aexp =off.docsize=user.splitting=off.splitting_startpage=left..user_x=-11800.user_w=23576.user_y=33.user_h=17080.user_unit=mil.starttimeout=1.sharpen=2.ies=off..[preview].preview_scale=4.preview_jpeg_quality=40..[image].jpeg_quality=75.fileformat=tiff.mirror=0.deskew=0.rotation=0.despeckle=off.tiff_compr=none.pdf_compr=none.dyn_bright=off.invert=off.profile=off.image_x=0.image_y=0.image_w=0.image_h=0..[autoborder].// 1/300 inch  steps.autoformat_extra = 0.autoformat_density=60.autoformat_docsize = maxl...[bfc].bfc_cornerarea = 1000.bfc_bcorr = 0.bfc_threshold=60.bfc_topmargin = 0.bfc_bottommargin = 0.bfc_leftmargin = 0.bfc_rightmargin = 0.bfc_retouchshadow=auto..bfc_retouchpattern = auto.bfc_leftcenter = 0.bfc_rightcenter = 0.bfc_surfaceproperties = 0..[Settings].Button1=0.Button2=0.Button3=0.Button4=0.LeftPedal=0.RightPedal=0.....[unused].lamp_pwm=  81</creatingApplicationName>
    <lastmodified toolname="Exiftool" toolversion="11.54" status="CONFLICT">2010:06:15 11:19:15</lastmodified>
    <lastmodified toolname="Tika" toolversion="1.21" status="CONFLICT">2010-06-15T11:19:15</lastmodified>
    <created toolname="Exiftool" toolversion="11.54" status="SINGLE_RESULT">2010:05:19 13:52:42-03:00</created>
    <filepath toolname="OIS File Information" toolversion="1.0" status="SINGLE_RESULT">/Users/nbanks/Projects/islandora/islandora_demo_objects/Newspapers and Serials/Newspaper_Sample_3/1970_pg4.tiff</filepath>
    <filename toolname="OIS File Information" toolversion="1.0" status="SINGLE_RESULT">1970_pg4.tiff</filename>
    <md5checksum toolname="OIS File Information" toolversion="1.0" status="SINGLE_RESULT">12b09a5f64ec4d52ef0b504ed9d5a09a</md5checksum>
    <fslastmodified toolname="OIS File Information" toolversion="1.0" status="SINGLE_RESULT">1677878451248</fslastmodified>
  </fileinfo>
  <filestatus>
    <well-formed toolname="Jhove" toolversion="1.20.1" status="SINGLE_RESULT">true</well-formed>
    <valid toolname="Jhove" toolversion="1.20.1" status="SINGLE_RESULT">true</valid>
  </filestatus>
  <metadata>
    <image>
      <byteOrder toolname="Jhove" toolversion="1.20.1" status="SINGLE_RESULT">little endian</byteOrder>
      <compressionScheme toolname="Jhove" toolversion="1.20.1">Uncompressed</compressionScheme>
      <imageWidth toolname="Jhove" toolversion="1.20.1">3511</imageWidth>
      <imageHeight toolname="Jhove" toolversion="1.20.1">5105</imageHeight>
      <colorSpace toolname="Jhove" toolversion="1.20.1">RGB</colorSpace>
      <referenceBlackWhite toolname="Jhove" toolversion="1.20.1" status="SINGLE_RESULT">0 255 0 255 0 255</referenceBlackWhite>
      <orientation toolname="Jhove" toolversion="1.20.1">normal*</orientation>
      <samplingFrequencyUnit toolname="Jhove" toolversion="1.20.1">in.</samplingFrequencyUnit>
      <xSamplingFrequency toolname="Jhove" toolversion="1.20.1">300</xSamplingFrequency>
      <ySamplingFrequency toolname="Jhove" toolversion="1.20.1">300</ySamplingFrequency>
      <bitsPerSample toolname="Jhove" toolversion="1.20.1">8 8 8</bitsPerSample>
      <samplesPerPixel toolname="Jhove" toolversion="1.20.1">3</samplesPerPixel>
      <scanningSoftwareName toolname="Jhove" toolversion="1.20.1" status="CONFLICT">%0A[global]%0Adpi_mode= flexible%0Adpi=300%0Ascanmode=wait%0Acolormode=truecolor%0Adocmode=4%0Adocheight = 0%0Awa_x = 1%0Awa_y = 1%0Aserial=S2N-BASE-V2-001999311b2d%0AFirmwareVersion=5.10%0A%0A[autofocus]%0Afocus_x = -1000%0Afocus_y = 500%0Afocus_w = 2500%0A%0A%0A[scan]%0Aautofocus=on%0Adescreening=0%0Acms=off%0Aspeed=1%0Abright=178%0Acontr=142%0Agamma=15%0Again_r=0%0Again_g=0%0Again_b=0%0Aaexp_black=10%0Aaexp =off%0Adocsize=user%0Asplitting=off%0Asplitting_startpage=left%09%0Auser_x=-11800%0Auser_w=23576%0Auser_y=33%0Auser_h=17080%0Auser_unit=mil%0Astarttimeout=1%0Asharpen=2%0Aies=off%0A%0A[preview]%0Apreview_scale=4%0Apreview_jpeg_quality=40%0A%0A[image]%0Ajpeg_quality=75%0Afileformat=tiff%0Amirror=0%0Adeskew=0%0Arotation=0%0Adespeckle=off%0Atiff_compr=none%0Apdf_compr=none%0Adyn_bright=off%0Ainvert=off%0Aprofile=off%0Aimage_x=0%0Aimage_y=0%0Aimage_w=0%0Aimage_h=0%0A%0A[autoborder]%0A// 1/300 inch  steps%0Aautoformat_extra = 0%0Aautoformat_density=60%0Aautoformat_docsize = maxl%0A%0A%0A[bfc]%0Abfc_cornerarea = 1000%0Abfc_bcorr = 0%0Abfc_threshold=60%0Abfc_topmargin = 0%0Abfc_bottommargin = 0%0Abfc_leftmargin = 0%0Abfc_rightmargin = 0%0Abfc_retouchshadow=auto%0A%0Abfc_retouchpattern = auto%0Abfc_leftcenter = 0%0Abfc_rightcenter = 0%0Abfc_surfaceproperties = 0%0A%0A[Settings]%0AButton1=0%0AButton2=0%0AButton3=0%0AButton4=0%0ALeftPedal=0%0ARightPedal=0%0A%0A%0A%0A%0A[unused]%0Alamp_pwm=  81%0A%0A</scanningSoftwareName>
      <scanningSoftwareName toolname="Exiftool" toolversion="11.54" status="CONFLICT">.[global].dpi_mode= flexible.dpi=300.scanmode=wait.colormode=truecolor.docmode=4.docheight = 0.wa_x = 1.wa_y = 1.serial=S2N-BASE-V2-001999311b2d.FirmwareVersion=5.10..[autofocus].focus_x = -1000.focus_y = 500.focus_w = 2500...[scan].autofocus=on.descreening=0.cms=off.speed=1.bright=178.contr=142.gamma=15.gain_r=0.gain_g=0.gain_b=0.aexp_black=10.aexp =off.docsize=user.splitting=off.splitting_startpage=left..user_x=-11800.user_w=23576.user_y=33.user_h=17080.user_unit=mil.starttimeout=1.sharpen=2.ies=off..[preview].preview_scale=4.preview_jpeg_quality=40..[image].jpeg_quality=75.fileformat=tiff.mirror=0.deskew=0.rotation=0.despeckle=off.tiff_compr=none.pdf_compr=none.dyn_bright=off.invert=off.profile=off.image_x=0.image_y=0.image_w=0.image_h=0..[autoborder].// 1/300 inch  steps.autoformat_extra = 0.autoformat_density=60.autoformat_docsize = maxl...[bfc].bfc_cornerarea = 1000.bfc_bcorr = 0.bfc_threshold=60.bfc_topmargin = 0.bfc_bottommargin = 0.bfc_leftmargin = 0.bfc_rightmargin = 0.bfc_retouchshadow=auto..bfc_retouchpattern = auto.bfc_leftcenter = 0.bfc_rightcenter = 0.bfc_surfaceproperties = 0..[Settings].Button1=0.Button2=0.Button3=0.Button4=0.LeftPedal=0.RightPedal=0.....[unused].lamp_pwm=  81</scanningSoftwareName>
      <exifVersion toolname="Exiftool" toolversion="11.54" status="SINGLE_RESULT">0221</exifVersion>
    </image>
  </metadata>
  <statistics fitsExecutionTime="3700">
    <tool toolname="MediaInfo" toolversion="[could not launch tool]" status="failed" />
    <tool toolname="OIS Audio Information" toolversion="0.1" status="did not run" />
    <tool toolname="ADL Tool" toolversion="0.1" status="did not run" />
    <tool toolname="VTT Tool" toolversion="0.1" status="did not run" />
    <tool toolname="Droid" toolversion="6.4" executionTime="3641" />
    <tool toolname="Jhove" toolversion="1.20.1" executionTime="2444" />
    <tool toolname="file utility" toolversion="5.43" executionTime="1661" />
    <tool toolname="Exiftool" toolversion="11.54" executionTime="1693" />
    <tool toolname="NLNZ Metadata Extractor" toolversion="3.6GA" status="did not run" />
    <tool toolname="OIS File Information" toolversion="1.0" executionTime="3364" />
    <tool toolname="OIS XML Metadata" toolversion="0.2" status="did not run" />
    <tool toolname="ffident" toolversion="0.2" executionTime="1244" />
    <tool toolname="Tika" toolversion="1.21" executionTime="3477" />
  </statistics>
</fits>

